vision6D/__init__.py
vision6D/path.py
vision6D/components/__init__.py
vision6D/components/abstract_model.py
vision6D/components/image_model.py
vision6D/components/mask_model.py
vision6D/components/mesh_model.py
vision6D/containers/__init__.py
vision6D/containers/image_container.py
vision6D/containers/mask_container.py
vision6D/containers/mesh_container.py
vision6D/containers/scene.py
vision6D/containers/singleton.py
vision6D/data/style.qss
vision6D/data/icons/copy.png
vision6D/data/icons/logo.ico
vision6D/data/icons/reset.png
vision6D/data/toy_example/linemod_o/lmo_test_bop19/test/000002/camera.json
vision6D/data/toy_example/linemod_o/lmo_test_bop19/test/000002/scene_gt.json
vision6D/data/toy_example/linemod_o/lmo_test_bop19/test/000002/models/obj_000001.ply
vision6D/data/toy_example/linemod_o/lmo_test_bop19/test/000002/models/obj_000005.ply
vision6D/data/toy_example/linemod_o/lmo_test_bop19/test/000002/models/obj_000006.ply
vision6D/data/toy_example/linemod_o/lmo_test_bop19/test/000002/models/obj_000008.ply
vision6D/data/toy_example/linemod_o/lmo_test_bop19/test/000002/models/obj_000009.ply
vision6D/data/toy_example/linemod_o/lmo_test_bop19/test/000002/models/obj_000010.ply
vision6D/data/toy_example/linemod_o/lmo_test_bop19/test/000002/models/obj_000011.ply
vision6D/data/toy_example/linemod_o/lmo_test_bop19/test/000002/models/obj_000012.ply
vision6D/data/toy_example/linemod_o/lmo_test_bop19/test/000002/rgb/000003.png
vision6D/data/toy_example/linemod_o/lmo_test_bop19/test/000002/rgb/000008.png
vision6D/data/toy_example/linemod_o/lmo_test_bop19/test/000002/rgb/000017.png
vision6D/data/toy_example/linemod_o/lmo_test_bop19/test/000002/rgb/000027.png
vision6D/data/toy_example/linemod_o/lmo_test_bop19/test/000002/rgb/000036.png
vision6D/data/toy_example/linemod_o/lmo_test_bop19/test/000002/rgb/000038.png
vision6D/data/toy_example/linemod_o/lmo_test_bop19/test/000002/rgb/000039.png
vision6D/data/toy_example/linemod_o/lmo_test_bop19/test/000002/rgb/000041.png
vision6d-0.5.5.dist-info/licenses/LICENSE
vision6d-0.5.5.dist-info/METADATA
vision6d-0.5.5.dist-info/WHEEL
vision6d-0.5.5.dist-info/entry_points.txt
vision6d-0.5.5.dist-info/top_level.txt
vision6d-0.5.5.dist-info/RECORD
