Metadata-Version: 2.4
Name: vision6D
Version: 0.5.5
Summary: 3D-to-2D visualization and annotation desktop app for 6D pose estimation related tasks. This python-based application is designed to work on Windows and Linux (Ubuntu-tested).
Home-page: https://github.com/ykzzyk/vision6D
License: GNU GENERAL Public License
Project-URL: Documentation, https://vision6d.readthedocs.io/en/latest/
Keywords: 6D,pose annotation,6D pose annotation,registration,segmentation,visualization tool
Platform: any
Classifier: Programming Language :: Python :: 3
Classifier: Programming Language :: Python :: 3.6
Classifier: Programming Language :: Python :: 3.7
Classifier: Programming Language :: Python :: 3.8
Classifier: Programming Language :: Python :: 3.9
Requires-Python: >=3.6
License-File: LICENSE
Requires-Dist: pyvista>=0.44.1
Requires-Dist: numpy>=1.23.5
Requires-Dist: matplotlib>=3.5.2
Requires-Dist: trimesh>=3.14.0
Requires-Dist: easydict>=1.9
Requires-Dist: pillow>=9.2.0
Requires-Dist: scipy>=1.8.1
Requires-Dist: pytest>=7.2.0
Requires-Dist: pytest-lazy-fixture>=0.6.3
Requires-Dist: pre-commit>=2.21.0
Requires-Dist: opencv-python-headless>=4.7.0.68
Requires-Dist: scikit-image>=0.19.3
Requires-Dist: chardet>=5.1.0
Requires-Dist: pygeodesic>=0.1.8
Requires-Dist: PyQt5>=5.15.9
Requires-Dist: pyvistaqt>=0.10.0
Requires-Dist: rtree
Requires-Dist: shapely
Requires-Dist: meshio
Dynamic: home-page
Dynamic: license-file
Dynamic: project-url
